socialblade/__init__.py
socialblade-1.0.4.3.dist-info/LICENSE
socialblade-1.0.4.3.dist-info/METADATA
socialblade-1.0.4.3.dist-info/WHEEL
socialblade-1.0.4.3.dist-info/top_level.txt
socialblade-1.0.4.3.dist-info/RECORD
