Metadata-Version: 2.1
Name: socialblade
Version: 1.0.4.3
Summary: Object oriented SocialBlade API wrapper
Home-page: https://github.com/sl4vkek/python-socialblade
Author: sl4v
Author-email: iamsl4v@protonmail.com
License: UNLICENSE
Platform: UNKNOWN
Requires-Dist: cloudscraper
Requires-Dist: dateparser
